pytest_watcher/__init__.py
pytest_watcher/__main__.py
pytest_watcher/commands.py
pytest_watcher/config.py
pytest_watcher/constants.py
pytest_watcher/event_handler.py
pytest_watcher/parse.py
pytest_watcher/terminal.py
pytest_watcher/trigger.py
pytest_watcher/watcher.py
pytest_watcher-0.6.2.dist-info/METADATA
pytest_watcher-0.6.2.dist-info/WHEEL
pytest_watcher-0.6.2.dist-info/entry_points.txt
pytest_watcher-0.6.2.dist-info/licenses/LICENSE
pytest_watcher-0.6.2.dist-info/RECORD
