Metadata-Version: 2.4
Name: pytest-watcher
Version: 0.6.2
Summary: Automatically rerun your tests on file modifications
Author-email: Olzhas Arystanov <o.arystanov@gmail.com>
License-Expression: MIT
License-File: LICENSE
Keywords: pytest,watch,watcher
Classifier: Development Status :: 4 - Beta
Classifier: Framework :: Pytest
Classifier: Intended Audience :: Developers
Classifier: Operating System :: OS Independent
Classifier: Programming Language :: Python
Classifier: Topic :: Software Development :: Testing
Classifier: Topic :: Utilities
Requires-Python: >=3.9
Requires-Dist: tomli>=2.0.1; python_version < '3.11'
Requires-Dist: watchdog>=2.0.0
